{
  "uid": "net.minecraft",
  "name": "Minecraft",
  "formatVersion": 1,
  "version": "12w07b",
  "type": "old_snapshot",
  "releaseTime": "2012-02-15T12:37:17.000Z",
  "requires": [
    {
      "uid": "org.lwjgl",
      "suggests": "2.9.4-nightly-20150209"
    }
  ],
  "compatibleJavaMajors": [
    8
  ],
  "compatibleJavaName": "jre-legacy",
  "minecraftArguments": "",
  "mainJar": {
    "name": "com.mojang:minecraft:12w07b:client",
    "downloads": {
      "artifact": {
        "url": "https://vault.omniarchive.uk/archive/java/client-release/1.2/pre/12w07b.jar",
        "sha1": "0eea35d588fc2cee5d397472aa3565f48c220217",
        "size": 3956323
      }
    }
  },
  "assetIndex": {
    "id": "1.2",
    "sha1": "e8109e911cd320416dc1853911f2ff1fe4de1377",
    "size": 39691,
    "totalSize": 42191017,
    "url": "https://meta.omniarchive.uk/indexes/1.2.json"
  }
}