{
  "uid": "net.minecraft",
  "name": "Minecraft",
  "formatVersion": 1,
  "version": "11w47a",
  "type": "old_snapshot",
  "releaseTime": "2011-11-24T13:20:06.000Z",
  "requires": [
    {
      "uid": "org.lwjgl",
      "suggests": "2.9.4-nightly-20150209"
    }
  ],
  "compatibleJavaMajors": [
    8
  ],
  "compatibleJavaName": "jre-legacy",
  "minecraftArguments": "",
  "mainJar": {
    "name": "com.mojang:minecraft:11w47a:client",
    "downloads": {
      "artifact": {
        "url": "https://vault.omniarchive.uk/archive/java/client-release/1.1/pre/11w47a.jar",
        "sha1": "4e327918708d22e7443fbadefb9831ca04af4b90",
        "size": 2242242
      }
    }
  },
  "assetIndex": {
    "id": "1.0.0-rc1",
    "sha1": "1186383e720a5ec6e974216baa7f16aed4bf9c22",
    "size": 35426,
    "totalSize": 41812691,
    "url": "https://meta.omniarchive.uk/indexes/1.0.0-rc1.json"
  }
}